LICENSE
README.md
setup.py
strainy/__init__.py
strainy/__version__.py
strainy/color_bam.py
strainy/flye_consensus.py
strainy/logging.py
strainy/main.py
strainy/params.py
strainy/phase.py
strainy/preprocessing.py
strainy/transform.py
strainy.egg-info/PKG-INFO
strainy.egg-info/SOURCES.txt
strainy.egg-info/dependency_links.txt
strainy.egg-info/entry_points.txt
strainy.egg-info/requires.txt
strainy.egg-info/top_level.txt
strainy/clustering/__init__.py
strainy/clustering/build_adj_matrix.py
strainy/clustering/build_data.py
strainy/clustering/cluster.py
strainy/clustering/cluster_postprocess.py
strainy/clustering/community_detection.py
strainy/gfa_operations/__init__.py
strainy/gfa_operations/gfa_ops.py
strainy/reports/__init__.py
strainy/reports/call_variants.py
strainy/reports/strainy_stats.py
strainy/simplification/__init__.py
strainy/simplification/simplify_links.py