Metadata-Version: 2.1
Name: strainy
Version: 1.4
Summary: Metagenomic strain phasing and assmebly using long reads
Home-page: https://github.com/katerinakazantseva/strainy
Author: Ekaterina Kazantseva & Ataberk Donmez
Author-email: ekaterina.v.kazantseva@gmail.com
License: CC BY-NC-SA 4.0
Platform: UNKNOWN
License-File: LICENSE
